{
  "timestamp": "2025-12-30T20:08:33.422323",
  "total_time": 3.506211519241333,
  "test_results": {
    "unit": {
      "success": false,
      "returncode": 4,
      "duration": 0.943709135055542,
      "stdout": "",
      "stderr": "ERROR: usage: __main__.py [options] [file_or_dir] [file_or_dir] [...]\n__main__.py: error: unrecognized arguments: --json-report --json-report-file=test_report.json\n  inifile: C:\\Dados\\Projects\\ncm-inexistente\\pytest.ini\n  rootdir: C:\\Dados\\Projects\\ncm-inexistente\n\n",
      "critical": true,
      "test_details": {}
    },
    "integration": {
      "success": false,
      "returncode": 4,
      "duration": 0.848379373550415,
      "stdout": "",
      "stderr": "ERROR: usage: __main__.py [options] [file_or_dir] [file_or_dir] [...]\n__main__.py: error: unrecognized arguments: --json-report --json-report-file=test_report.json\n  inifile: C:\\Dados\\Projects\\ncm-inexistente\\pytest.ini\n  rootdir: C:\\Dados\\Projects\\ncm-inexistente\n\n",
      "critical": true,
      "test_details": {}
    },
    "property": {
      "success": false,
      "returncode": 4,
      "duration": 0.8600480556488037,
      "stdout": "",
      "stderr": "ERROR: usage: __main__.py [options] [file_or_dir] [file_or_dir] [...]\n__main__.py: error: unrecognized arguments: --json-report --json-report-file=test_report.json\n  inifile: C:\\Dados\\Projects\\ncm-inexistente\\pytest.ini\n  rootdir: C:\\Dados\\Projects\\ncm-inexistente\n\n",
      "critical": false,
      "test_details": {}
    },
    "performance": {
      "success": false,
      "returncode": 4,
      "duration": 0.850346565246582,
      "stdout": "",
      "stderr": "ERROR: usage: __main__.py [options] [file_or_dir] [file_or_dir] [...]\n__main__.py: error: unrecognized arguments: --json-report --json-report-file=test_report.json\n  inifile: C:\\Dados\\Projects\\ncm-inexistente\\pytest.ini\n  rootdir: C:\\Dados\\Projects\\ncm-inexistente\n\n",
      "critical": false,
      "test_details": {}
    }
  },
  "performance_metrics": {
    "total_duration": 3.5024831295013428,
    "category_performance": {
      "unit": {
        "duration": 0.943709135055542,
        "threshold": 30,
        "ratio": 0.03145697116851807,
        "status": "good"
      },
      "integration": {
        "duration": 0.848379373550415,
        "threshold": 60,
        "ratio": 0.014139656225840251,
        "status": "good"
      },
      "property": {
        "duration": 0.8600480556488037,
        "threshold": 120,
        "ratio": 0.007167067130406698,
        "status": "good"
      },
      "performance": {
        "duration": 0.850346565246582,
        "threshold": 300,
        "ratio": 0.00283448855082194,
        "status": "good"
      }
    },
    "performance_issues": [],
    "performance_score": 100
  },
  "regression_analysis": {
    "has_regressions": false,
    "message": "Insufficient historical data for regression analysis",
    "regressions": []
  },
  "quality_score": {
    "overall": 53.5,
    "grade": "F",
    "components": {
      "test_success": 0.0,
      "performance": 100,
      "coverage": 75,
      "code_quality": 85
    },
    "weights": {
      "test_success": 0.4,
      "performance": 0.3,
      "coverage": 0.2,
      "code_quality": 0.1
    }
  }
}